Workbook

Sheet Mode_emploi
A1: SmartBudget AI — Mode d'emploi du modèle financier
A3: Objectif | B3: Modéliser la logique business de SmartBudget AI et fournir une base propre à importer dans Lovable pour générer un tableau de bord.
A4: Important | B4: Ce fichier modélise le business SaaS. Le mini budget tracker personnel visible dans l'app publique est une démonstration produit distincte.
A5: Lien app | B5: https://smart-coin-whisperer-68.lovable.app
A6: Cohérence visée | B6: Fin d'année : 1064 utilisateurs, 160 premium, MRR décembre 958.40 $, revenu Année 1 6079.85 $, économies moyennes décembre 48.45 $/mois.
A7: Sheets | B7: Hypotheses / Previsions_12M / Economie_Unitaire / Import_Dashboard / Dashboard / Prompt_Lovable / Coherence_App
A8: Utilisation | B8: Modifier uniquement la colonne Valeur dans Hypotheses pour recalculer le modèle complet.

Sheet Hypotheses
A1: Hypothèses de base — SmartBudget AI
A3: Catégorie | B3: Hypothèse | C3: Valeur | D3: Unité | E3: Commentaire | F3: Source
A4: Marché | B4: Utilisateurs actifs au lancement | C4: 120 | D4: users | E4: Lancement prudent pour un prototype campus / jeunes actifs | F4: https://smart-coin-whisperer-68.lovable.app
A5: Marché | B5: Nouveaux utilisateurs - mois 1 | C5: 60 | D5: users | E5: Acquisition initiale organique + bouche à oreille | F5: https://smart-coin-whisperer-68.lovable.app
A6: Croissance | B6: Croissance mensuelle des nouvelles acquisitions | C6: 0.1 | D6: % | E6: Croissance progressive de la notoriété
A7: Rétention | B7: Churn mensuel utilisateurs actifs | C7: 0.06 | D7: % | E7: Perte modérée d’utilisateurs pour une app débutante
A8: Monétisation | B8: Taux de conversion premium | C8: 0.15 | D8: % | E8: Proposition de valeur claire + prix accessible
A9: Monétisation | B9: Prix abonnement premium mensuel | C9: 5.99 | D9: CAD | E9: Prix étudiant / jeune adulte
A10: Comportement | B10: Dépense mensuelle moyenne avant app | C10: 650 | D10: CAD | E10: Budget moyen cible
A11: Valeur client | B11: Économies moyennes / utilisateur - mois 1 | C11: 35 | D11: CAD | E11: Gain initial réaliste
A12: Valeur client | B12: Amélioration mensuelle des économies | C12: 0.03 | D12: % | E12: Amélioration graduelle des habitudes
A13: Marketing | B13: Dépenses marketing - mois 1 | C13: 90 | D13: CAD | E13: Budget prudent
A14: Marketing | B14: Croissance mensuelle budget marketing | C14: 0.06 | D14: % | E14: Effort acquisition croissant
A15: Coûts | B15: Coût IA variable / utilisateur actif | C15: 0.18 | D15: CAD | E15: Inference et conseils
A16: Coûts | B16: Coût support + infra variable / utilisateur actif | C16: 0.07 | D16: CAD | E16: Cloud léger + support
A17: Coûts | B17: Frais fixes mensuels | C17: 45 | D17: CAD | E17: Outils, maintenance, design
... A19: Marketing | B19: Part des acquisitions venant du paid | C19: 0.35 | D19: % | E19: Le reste vient de l’organique

Sheet Previsions_12M
A1: Prévisions financières sur 12 mois — scénario central
A3: Mois | B3: Utilisateurs début | C3: Nouveaux utilisateurs | D3: Utilisateurs perdus | E3: Utilisateurs fin | F3: Conversion premium | G3: Abonnés premium | H3: Prix premium | I3: MRR | J3: ARPU | K3: Dépense moyenne / utilisateur | L3: Économies moyennes / utilisateur | M3: Économies totales générées | N3: Marketing | O3: Coût IA | P3: Coût support+infra | Q3: Frais fixes | R3: Frais paiement | S3: Coûts totaux | T3: Contribution après marketing
A4: Janvier | B4: =Hypotheses!$C$4 -> 120 | C4: =Hypotheses!$C$5 -> 60 | D4: =ROUND(B4*Hypotheses!$C$7,0) -> 7 | E4: =B4+C4-D4 -> 173 | F4: =Hypotheses!$C$8 -> 0.15 | G4: =ROUND(E4*F4,0) -> 26 | H4: =Hypotheses!$C$9 -> 5.99 | I4: =G4*H4 -> 155.74 | J4: =I4/E4 -> 0.90023121 | K4: =Hypotheses!$C$10 -> 650 | L4: =Hypotheses!$C$11 -> 35 | M4: =E4*L4 -> 6055 | N4: =Hypotheses!$C$13 -> 90 | O4: =E4*Hypotheses!$C$15 -> 31.14 | P4: =E4*Hypotheses!$C$16 -> 12.11 | Q4: =Hypotheses!$C$17 -> 45 | R4: =I4*Hypotheses!$C$18 -> 4.6722 | S4: =N4+O4+P4+Q4+R4 -> 182.9222 | T4: =I4-S4 -> -27.1822
A5: Février | B5: =E4 -> 173 | C5: =ROUND(C4*(1+Hypotheses!$C$6),0) -> 66 | D5: =ROUND(B5*Hypotheses!$C$7,0) -> 10 | E5: =B5+C5-D5 -> 229 | F5: =Hypotheses!$C$8 -> 0.15 | G5: =ROUND(E5*F5,0) -> 34 | H5: =Hypotheses!$C$9 -> 5.99 | I5: =G5*H5 -> 203.66 | J5: =I5/E5 -> 0.88934498 | K5: =K4*1.005 -> 653.25 | L5: =L4*(1+Hypotheses!$C$12) -> 36.05 | M5: =E5*L5 -> 8255.45 | N5: =N4*(1+Hypotheses!$C$14) -> 95.4 | O5: =E5*Hypotheses!$C$15 -> 41.22 | P5: =E5*Hypotheses!$C$16 -> 16.03 | Q5: =Hypotheses!$C$17 -> 45 | R5: =I5*Hypotheses!$C$18 -> 6.1098 | S5: =N5+O5+P5+Q5+R5 -> 203.7598 | T5: =I5-S5 -> -0.0998
A6: Mars | B6: =E5 -> 229 | C6: =ROUND(C5*(1+Hypotheses!$C$6),0) -> 73 | D6: =ROUND(B6*Hypotheses!$C$7,0) -> 14 | E6: =B6+C6-D6 -> 288 | F6: =Hypotheses!$C$8 -> 0.15 | G6: =ROUND(E6*F6,0) -> 43 | H6: =Hypotheses!$C$9 -> 5.99 | I6: =G6*H6 -> 257.57 | J6: =I6/E6 -> 0.89434028 | K6: =K5*1.005 -> 656.51625 | L6: =L5*(1+Hypotheses!$C$12) -> 37.1315 | M6: =E6*L6 -> 10693.872 | N6: =N5*(1+Hypotheses!$C$14) -> 101.124 | O6: =E6*Hypotheses!$C$15 -> 51.84 | P6: =E6*Hypotheses!$C$16 -> 20.16 | Q6: =Hypotheses!$C$17 -> 45 | R6: =I6*Hypotheses!$C$18 -> 7.7271 | S6: =N6+O6+P6+Q6+R6 -> 225.8511 | T6: =I6-S6 -> 31.7189
A7: Avril | B7: =E6 -> 288 | C7: =ROUND(C6*(1+Hypotheses!$C$6),0) -> 80 | D7: =ROUND(B7*Hypotheses!$C$7,0) -> 17 | E7: =B7+C7-D7 -> 351 | F7: =Hypotheses!$C$8 -> 0.15 | G7: =ROUND(E7*F7,0) -> 53 | H7: =Hypotheses!$C$9 -> 5.99 | I7: =G7*H7 -> 317.47 | J7: =I7/E7 -> 0.90447293 | K7: =K6*1.005 -> 659.79883 | L7: =L6*(1+Hypotheses!$C$12) -> 38.245445 | M7: =E7*L7 -> 13424.151 | N7: =N6*(1+Hypotheses!$C$14) -> 107.19144 | O7: =E7*Hypotheses!$C$15 -> 63.18 | P7: =E7*Hypotheses!$C$16 -> 24.57 | Q7: =Hypotheses!$C$17 -> 45 | R7: =I7*Hypotheses!$C$18 -> 9.5241 | S7: =N7+O7+P7+Q7+R7 -> 249.46554 | T7: =I7-S7 -> 68.00446
A8: Mai | B8: =E7 -> 351 | C8: =ROUND(C7*(1+Hypotheses!$C$6),0) -> 88 | D8: =ROUND(B8*Hypotheses!$C$7,0) -> 21 | E8: =B8+C8-D8 -> 418 | F8: =Hypotheses!$C$8 -> 0.15 | G8: =ROUND(E8*F8,0) -> 63 | H8: =Hypotheses!$C$9 -> 5.99 | I8: =G8*H8 -> 377.37 | J8: =I8/E8 -> 0.90279904 | K8: =K7*1.005 -> 663.09783 | L8: =L7*(1+Hypotheses!$C$12) -> 39.392808 | M8: =E8*L8 -> 16466.194 | N8: =N7*(1+Hypotheses!$C$14) -> 113.62293 | O8: =E8*Hypotheses!$C$15 -> 75.24 | P8: =E8*Hypotheses!$C$16 -> 29.26 | Q8: =Hypotheses!$C$17 -> 45 | R8: =I8*Hypotheses!$C$18 -> 11.3211 | S8: =N8+O8+P8+Q8+R8 -> 274.44403 | T8: =I8-S8 -> 102.92597
A9: Juin | B9: =E8 -> 418 | C9: =ROUND(C8*(1+Hypotheses!$C$6),0) -> 97 | D9: =ROUND(B9*Hypotheses!$C$7,0) -> 25 | E9: =B9+C9-D9 -> 490 | F9: =Hypotheses!$C$8 -> 0.15 | G9: =ROUND(E9*F9,0) -> 74 | H9: =Hypotheses!$C$9 -> 5.99 | I9: =G9*H9 -> 443.26 | J9: =I9/E9 -> 0.90461224 | K9: =K8*1.005 -> 666.41331 | L9: =L8*(1+Hypotheses!$C$12) -> 40.574593 | M9: =E9*L9 -> 19881.55 | N9: =N8*(1+Hypotheses!$C$14) -> 120.4403 | O9: =E9*Hypotheses!$C$15 -> 88.2 | P9: =E9*Hypotheses!$C$16 -> 34.3 | Q9: =Hypotheses!$C$17 -> 45 | R9: =I9*Hypotheses!$C$18 -> 13.2978 | S9: =N9+O9+P9+Q9+R9 -> 301.2381 | T9: =I9-S9 -> 142.0219
A10: Juillet | B10: =E9 -> 490 | C10: =ROUND(C9*(1+Hypotheses!$C$6),0) -> 107 | D10: =ROUND(B10*Hypotheses!$C$7,0) -> 29 | E10: =B10+C10-D10 -> 568 | F10: =Hypotheses!$C$8 -> 0.15 | G10: =ROUND(E10*F10,0) -> 85 | H10: =Hypotheses!$C$9 -> 5.99 | I10: =G10*H10 -> 509.15 | J10: =I10/E10 -> 0.89639085 | K10: =K9*1.005 -> 669.74538 | L10: =L9*(1+Hypotheses!$C$12) -> 41.79183 | M10: =E10*L10 -> 23737.76 | N10: =N9*(1+Hypotheses!$C$14) -> 127.66672 | O10: =E10*Hypotheses!$C$15 -> 102.24 | P10: =E10*Hypotheses!$C$16 -> 39.76 | Q10: =Hypotheses!$C$17 -> 45 | R10: =I10*Hypotheses!$C$18 -> 15.2745 | S10: =N10+O10+P10+Q10+R10 -> 329.94122 | T10: =I10-S10 -> 179.20878
A11: Août | B11: =E10 -> 568 | C11: =ROUND(C10*(1+Hypotheses!$C$6),0) -> 118 | D11: =ROUND(B11*Hypotheses!$C$7,0) -> 34 | E11: =B11+C11-D11 -> 652 | F11: =Hypotheses!$C$8 -> 0.15 | G11: =ROUND(E11*F11,0) -> 98 | H11: =Hypotheses!$C$9 -> 5.99 | I11: =G11*H11 -> 587.02 | J11: =I11/E11 -> 0.90033742 | K11: =K10*1.005 -> 673.09411 | L11: =L10*(1+Hypotheses!$C$12) -> 43.045585 | M11: =E11*L11 -> 28065.722 | N11: =N10*(1+Hypotheses!$C$14) -> 135.32672 | O11: =E11*Hypotheses!$C$15 -> 117.36 | P11: =E11*Hypotheses!$C$16 -> 45.64 | Q11: =Hypotheses!$C$17 -> 45 | R11: =I11*Hypotheses!$C$18 -> 17.6106 | S11: =N11+O11+P11+Q11+R11 -> 360.93732 | T11: =I11-S11 -> 226.08268
A12: Septembre | B12: =E11 -> 652 | C12: =ROUND(C11*(1+Hypotheses!$C$6),0) -> 130 | D12: =ROUND(B12*Hypotheses!$C$7,0) -> 39 | E12: =B12+C12-D12 -> 743 | F12: =Hypotheses!$C$8 -> 0.15 | G12: =ROUND(E12*F12,0) -> 111 | H12: =Hypotheses!$C$9 -> 5.99 | I12: =G12*H12 -> 664.89 | J12: =I12/E12 -> 0.89487214 | K12: =K11*1.005 -> 676.45958 | L12: =L11*(1+Hypotheses!$C$12) -> 44.336953 | M12: =E12*L12 -> 32942.356 | N12: =N11*(1+Hypotheses!$C$14) -> 143.44633 | O12: =E12*Hypotheses!$C$15 -> 133.74 | P12: =E12*Hypotheses!$C$16 -> 52.01 | Q12: =Hypotheses!$C$17 -> 45 | R12: =I12*Hypotheses!$C$18 -> 19.9467 | S12: =N12+O12+P12+Q12+R12 -> 394.14303 | T12: =I12-S12 -> 270.74697
A13: Octobre | B13: =E12 -> 743 | C13: =ROUND(C12*(1+Hypotheses!$C$6),0) -> 143 | D13: =ROUND(B13*Hypotheses!$C$7,0) -> 45 | E13: =B13+C13-D13 -> 841 | F13: =Hypotheses!$C$8 -> 0.15 | G13: =ROUND(E13*F13,0) -> 126 | H13: =Hypotheses!$C$9 -> 5.99 | I13: =G13*H13 -> 754.74 | J13: =I13/E13 -> 0.89743163 | K13: =K12*1.005 -> 679.84188 | L13: =L12*(1+Hypotheses!$C$12) -> 45.667061 | M13: =E13*L13 -> 38405.999 | N13: =N12*(1+Hypotheses!$C$14) -> 152.05311 | O13: =E13*Hypotheses!$C$15 -> 151.38 | P13: =E13*Hypotheses!$C$16 -> 58.87 | Q13: =Hypotheses!$C$17 -> 45 | R13: =I13*Hypotheses!$C$18 -> 22.6422 | S13: =N13+O13+P13+Q13+R13 -> 429.94531 | T13: =I13-S13 -> 324.79469
A14: Novembre | B14: =E13 -> 841 | C14: =ROUND(C13*(1+Hypotheses!$C$6),0) -> 157 | D14: =ROUND(B14*Hypotheses!$C$7,0) -> 50 | E14: =B14+C14-D14 -> 948 | F14: =Hypotheses!$C$8 -> 0.15 | G14: =ROUND(E14*F14,0) -> 142 | H14: =Hypotheses!$C$9 -> 5.99 | I14: =G14*H14 -> 850.58 | J14: =I14/E14 -> 0.89723629 | K14: =K13*1.005 -> 683.24109 | L14: =L13*(1+Hypotheses!$C$12) -> 47.037073 | M14: =E14*L14 -> 44591.145 | N14: =N13*(1+Hypotheses!$C$14) -> 161.17629 | O14: =E14*Hypotheses!$C$15 -> 170.64 | P14: =E14*Hypotheses!$C$16 -> 66.36 | Q14: =Hypotheses!$C$17 -> 45 | R14: =I14*Hypotheses!$C$18 -> 25.5174 | S14: =N14+O14+P14+Q14+R14 -> 468.69369 | T14: =I14-S14 -> 381.88631
A15: Décembre | B15: =E14 -> 948 | C15: =ROUND(C14*(1+Hypotheses!$C$6),0) -> 173 | D15: =ROUND(B15*Hypotheses!$C$7,0) -> 57 | E15: =B15+C15-D15 -> 1064 | F15: =Hypotheses!$C$8 -> 0.15 | G15: =ROUND(E15*F15,0) -> 160 | H15: =Hypotheses!$C$9 -> 5.99 | I15: =G15*H15 -> 958.4 | J15: =I15/E15 -> 0.90075188 | K15: =K14*1.005 -> 686.65729 | L15: =L14*(1+Hypotheses!$C$12) -> 48.448185 | M15: =E15*L15 -> 51548.869 | N15: =N14*(1+Hypotheses!$C$14) -> 170.84687 | O15: =E15*Hypotheses!$C$15 -> 191.52 | P15: =E15*Hypotheses!$C$16 -> 74.48 | Q15: =Hypotheses!$C$17 -> 45 | R15: =I15*Hypotheses!$C$18 -> 28.752 | S15: =N15+O15+P15+Q15+R15 -> 510.59887 | T15: =I15-S15 -> 447.80113
A17: Total / Moyenne | C17: =SUM(C4:C15) -> 1292 | D17: =SUM(D4:D15) -> 348 | I17: =SUM(I4:I15) -> 6079.85 | J17: =AVERAGE(J4:J15) -> 0.89856841 | K17: =AVERAGE(K4:K15) -> 668.1763 | L17: =AVERAGE(L4:L15) -> 41.39342 | M17: =SUM(M4:M15) -> 294068.07 | N17: =SUM(N4:N15) -> 1518.2947 | O17: =SUM(O4:O15) -> 1217.7 | P17: =SUM(P4:P15) -> 473.55 | Q17: =SUM(Q4:Q15) -> 540 | R17: =SUM(R4:R15) -> 182.3955 | S17: =SUM(S4:S15) -> 3931.9402 | T17: =SUM(T4:T15) -> 2147.9098

Sheet Economie_Unitaire
A1: Économie unitaire — SmartBudget AI
A3: Indicateur | B3: Formule / logique | C3: Valeur | D3: Interprétation | E3: Lecture orale | F3: Source
A4: ARPPU mensuel | B4: Prix premium | C4: =Hypotheses!$C$9 -> 5.99 | D4: Revenu mensuel par abonné payant | E4: Abonnement accessible | F4: https://smart-coin-whisperer-68.lovable.app
A5: Coût variable par abonné payant | B5: (coût IA + support) / conversion + frais paiement | C5: =((Hypotheses!$C$15+Hypotheses!$C$16)/Hypotheses!$C$8)+(Hypotheses!$C$9*Hypotheses!$C$18) -> 1.8463667 | D5: Approximation pédagogique du coût variable premium | E5: Relie la base active à la base payante
A6: Marge brute / abonné | B6: ARPPU - coût variable / abonné | C6: =C4-C5 -> 4.1436333 | D6: Valeur brute avant marketing | E6: Doit rester positive
A7: Marge brute % | B7: Marge brute / ARPPU | C7: =C6/C4 -> 0.69175849 | D7: Qualité économique du produit | E7: Plus c’est élevé, mieux c’est
A8: Durée de vie client (mois) | B8: 1 / churn premium (proxy actif) | C8: =1/Hypotheses!$C$7 -> 16.666667 | D8: Durée de vie théorique | E8: Hypothèse prudente
A9: LTV brut | B9: Marge brute / abonné x durée de vie | C9: =C6*C8 -> 69.060556 | D9: Valeur brute par client payant | E9: Doit dépasser le CAC
A10: CAC payant estimé | B10: Marketing annuel / nouveaux premium annuels | C10: =Previsions_12M!N17/SUM(Previsions_12M!G4:G15) -> 1.4958569 | D10: Coût d’acquisition d’un client payant | E10: À comparer à la LTV
A11: LTV / CAC | B11: LTV brut / CAC | C11: =C9/C10 -> 46.167891 | D11: Au-dessus de 3x = modèle sain | E11: Ici le ratio reste solide
A12: Payback (mois) | B12: CAC / marge brute mensuelle | C12: =C10/C6 -> 0.36100126 | D12: Temps de remboursement du CAC | E12: Court = bon signe

Sheet Import_Dashboard
A1: Table simplifiée pour import dashboard
A3: Mois | B3: Utilisateurs actifs fin | C3: Abonnés premium | D3: Revenu mensuel | E3: Économies totales | F3: Marketing | G3: Coûts totaux | H3: Contribution
A4: =Previsions_12M!A4 -> Janvier | B4: =Previsions_12M!E4 -> 173 | C4: =Previsions_12M!G4 -> 26 | D4: =Previsions_12M!I4 -> 155.74 | E4: =Previsions_12M!M4 -> 6055 | F4: =Previsions_12M!N4 -> 90 | G4: =Previsions_12M!S4 -> 182.9222 | H4: =Previsions_12M!T4 -> -27.1822
A5: =Previsions_12M!A5 -> Février | B5: =Previsions_12M!E5 -> 229 | C5: =Previsions_12M!G5 -> 34 | D5: =Previsions_12M!I5 -> 203.66 | E5: =Previsions_12M!M5 -> 8255.45 | F5: =Previsions_12M!N5 -> 95.4 | G5: =Previsions_12M!S5 -> 203.7598 | H5: =Previsions_12M!T5 -> -0.0998
A6: =Previsions_12M!A6 -> Mars | B6: =Previsions_12M!E6 -> 288 | C6: =Previsions_12M!G6 -> 43 | D6: =Previsions_12M!I6 -> 257.57 | E6: =Previsions_12M!M6 -> 10693.872 | F6: =Previsions_12M!N6 -> 101.124 | G6: =Previsions_12M!S6 -> 225.8511 | H6: =Previsions_12M!T6 -> 31.7189
A7: =Previsions_12M!A7 -> Avril | B7: =Previsions_12M!E7 -> 351 | C7: =Previsions_12M!G7 -> 53 | D7: =Previsions_12M!I7 -> 317.47 | E7: =Previsions_12M!M7 -> 13424.151 | F7: =Previsions_12M!N7 -> 107.19144 | G7: =Previsions_12M!S7 -> 249.46554 | H7: =Previsions_12M!T7 -> 68.00446
A8: =Previsions_12M!A8 -> Mai | B8: =Previsions_12M!E8 -> 418 | C8: =Previsions_12M!G8 -> 63 | D8: =Previsions_12M!I8 -> 377.37 | E8: =Previsions_12M!M8 -> 16466.194 | F8: =Previsions_12M!N8 -> 113.62293 | G8: =Previsions_12M!S8 -> 274.44403 | H8: =Previsions_12M!T8 -> 102.92597
A9: =Previsions_12M!A9 -> Juin | B9: =Previsions_12M!E9 -> 490 | C9: =Previsions_12M!G9 -> 74 | D9: =Previsions_12M!I9 -> 443.26 | E9: =Previsions_12M!M9 -> 19881.55 | F9: =Previsions_12M!N9 -> 120.4403 | G9: =Previsions_12M!S9 -> 301.2381 | H9: =Previsions_12M!T9 -> 142.0219
A10: =Previsions_12M!A10 -> Juillet | B10: =Previsions_12M!E10 -> 568 | C10: =Previsions_12M!G10 -> 85 | D10: =Previsions_12M!I10 -> 509.15 | E10: =Previsions_12M!M10 -> 23737.76 | F10: =Previsions_12M!N10 -> 127.66672 | G10: =Previsions_12M!S10 -> 329.94122 | H10: =Previsions_12M!T10 -> 179.20878
A11: =Previsions_12M!A11 -> Août | B11: =Previsions_12M!E11 -> 652 | C11: =Previsions_12M!G11 -> 98 | D11: =Previsions_12M!I11 -> 587.02 | E11: =Previsions_12M!M11 -> 28065.722 | F11: =Previsions_12M!N11 -> 135.32672 | G11: =Previsions_12M!S11 -> 360.93732 | H11: =Previsions_12M!T11 -> 226.08268
A12: =Previsions_12M!A12 -> Septembre | B12: =Previsions_12M!E12 -> 743 | C12: =Previsions_12M!G12 -> 111 | D12: =Previsions_12M!I12 -> 664.89 | E12: =Previsions_12M!M12 -> 32942.356 | F12: =Previsions_12M!N12 -> 143.44633 | G12: =Previsions_12M!S12 -> 394.14303 | H12: =Previsions_12M!T12 -> 270.74697
A13: =Previsions_12M!A13 -> Octobre | B13: =Previsions_12M!E13 -> 841 | C13: =Previsions_12M!G13 -> 126 | D13: =Previsions_12M!I13 -> 754.74 | E13: =Previsions_12M!M13 -> 38405.999 | F13: =Previsions_12M!N13 -> 152.05311 | G13: =Previsions_12M!S13 -> 429.94531 | H13: =Previsions_12M!T13 -> 324.79469
A14: =Previsions_12M!A14 -> Novembre | B14: =Previsions_12M!E14 -> 948 | C14: =Previsions_12M!G14 -> 142 | D14: =Previsions_12M!I14 -> 850.58 | E14: =Previsions_12M!M14 -> 44591.145 | F14: =Previsions_12M!N14 -> 161.17629 | G14: =Previsions_12M!S14 -> 468.69369 | H14: =Previsions_12M!T14 -> 381.88631
A15: =Previsions_12M!A15 -> Décembre | B15: =Previsions_12M!E15 -> 1064 | C15: =Previsions_12M!G15 -> 160 | D15: =Previsions_12M!I15 -> 958.4 | E15: =Previsions_12M!M15 -> 51548.869 | F15: =Previsions_12M!N15 -> 170.84687 | G15: =Previsions_12M!S15 -> 510.59887 | H15: =Previsions_12M!T15 -> 447.80113

Sheet Dashboard
A1: Dashboard — SmartBudget AI
A2: Cohérent avec l’app business : Users fin année, Premium fin année, MRR décembre, Revenu total Année 1, économies et qualité économique.
A4: Users fin année | D4: Premium fin année | G4: MRR décembre | J4: Revenu total Année 1
A5: =Previsions_12M!E15 -> 1064 | D5: =Previsions_12M!G15 -> 160 | G5: =Previsions_12M!I15 -> 958.4 | J5: =Previsions_12M!I17 -> 6079.85
A8: Économies Année 1 | D8: Avg savings déc./mois | G8: LTV / CAC | J8: Payback (mois)
A9: =Previsions_12M!M17 -> 294068.07 | D9: =Previsions_12M!L15 -> 48.448185 | G9: =Economie_Unitaire!C11 -> 46.167891 | J9: =Economie_Unitaire!C12 -> 0.36100126
A12: Note de cohérence : ce dashboard modélise la logique business SaaS. Le budget personnel affiché dans l’app publique est une démonstration produit distincte, donc il ne doit pas être confondu avec ce modèle financier.
A20: Mois | B20: Utilisateurs | D20: Mois | E20: MRR | G20: Mois | H20: Économies totales
A21: =Import_Dashboard!A4 -> Janvier | B21: =Import_Dashboard!B4 -> 173 | D21: =Import_Dashboard!A4 -> Janvier | E21: =Import_Dashboard!D4 -> 155.74 | G21: =Import_Dashboard!A4 -> Janvier | H21: =Import_Dashboard!E4 -> 6055
A22: =Import_Dashboard!A5 -> Février | B22: =Import_Dashboard!B5 -> 229 | D22: =Import_Dashboard!A5 -> Février | E22: =Import_Dashboard!D5 -> 203.66 | G22: =Import_Dashboard!A5 -> Février | H22: =Import_Dashboard!E5 -> 8255.45
A23: =Import_Dashboard!A6 -> Mars | B23: =Import_Dashboard!B6 -> 288 | D23: =Import_Dashboard!A6 -> Mars | E23: =Import_Dashboard!D6 -> 257.57 | G23: =Import_Dashboard!A6 -> Mars | H23: =Import_Dashboard!E6 -> 10693.872
A24: =Import_Dashboard!A7 -> Avril | B24: =Import_Dashboard!B7 -> 351 | D24: =Import_Dashboard!A7 -> Avril | E24: =Import_Dashboard!D7 -> 317.47 | G24: =Import_Dashboard!A7 -> Avril | H24: =Import_Dashboard!E7 -> 13424.151
A25: =Import_Dashboard!A8 -> Mai | B25: =Import_Dashboard!B8 -> 418 | D25: =Import_Dashboard!A8 -> Mai | E25: =Import_Dashboard!D8 -> 377.37 | G25: =Import_Dashboard!A8 -> Mai | H25: =Import_Dashboard!E8 -> 16466.194
A26: =Import_Dashboard!A9 -> Juin | B26: =Import_Dashboard!B9 -> 490 | D26: =Import_Dashboard!A9 -> Juin | E26: =Import_Dashboard!D9 -> 443.26 | G26: =Import_Dashboard!A9 -> Juin | H26: =Import_Dashboard!E9 -> 19881.55
A27: =Import_Dashboard!A10 -> Juillet | B27: =Import_Dashboard!B10 -> 568 | D27: =Import_Dashboard!A10 -> Juillet | E27: =Import_Dashboard!D10 -> 509.15 | G27: =Import_Dashboard!A10 -> Juillet | H27: =Import_Dashboard!E10 -> 23737.76
A28: =Import_Dashboard!A11 -> Août | B28: =Import_Dashboard!B11 -> 652 | D28: =Import_Dashboard!A11 -> Août | E28: =Import_Dashboard!D11 -> 587.02 | G28: =Import_Dashboard!A11 -> Août | H28: =Import_Dashboard!E11 -> 28065.722
A29: =Import_Dashboard!A12 -> Septembre | B29: =Import_Dashboard!B12 -> 743 | D29: =Import_Dashboard!A12 -> Septembre | E29: =Import_Dashboard!D12 -> 664.89 | G29: =Import_Dashboard!A12 -> Septembre | H29: =Import_Dashboard!E12 -> 32942.356
A30: =Import_Dashboard!A13 -> Octobre | B30: =Import_Dashboard!B13 -> 841 | D30: =Import_Dashboard!A13 -> Octobre | E30: =Import_Dashboard!D13 -> 754.74 | G30: =Import_Dashboard!A13 -> Octobre | H30: =Import_Dashboard!E13 -> 38405.999
A31: =Import_Dashboard!A14 -> Novembre | B31: =Import_Dashboard!B14 -> 948 | D31: =Import_Dashboard!A14 -> Novembre | E31: =Import_Dashboard!D14 -> 850.58 | G31: =Import_Dashboard!A14 -> Novembre | H31: =Import_Dashboard!E14 -> 44591.145
A32: =Import_Dashboard!A15 -> Décembre | B32: =Import_Dashboard!B15 -> 1064 | D32: =Import_Dashboard!A15 -> Décembre | E32: =Import_Dashboard!D15 -> 958.4 | G32: =Import_Dashboard!A15 -> Décembre | H32: =Import_Dashboard!E15 -> 51548.869
